setup.py
distributions/Binomialdistribution.py
distributions/Gaussiandistribution.py
distributions/Generaldistribution.py
distributions/__init__.py
jen_distributions.egg-info/PKG-INFO
jen_distributions.egg-info/SOURCES.txt
jen_distributions.egg-info/dependency_links.txt
jen_distributions.egg-info/not-zip-safe
jen_distributions.egg-info/top_level.txt